LICENSE
MANIFEST.in
README.rst
setup.cfg
setup.py
libthirty/__init__.py
libthirty/actions.py
libthirty/app.py
libthirty/base.py
libthirty/documents.py
libthirty/exceptions.py
libthirty/logbook.py
libthirty/logs.py
libthirty/state.py
libthirty/tests.py
libthirty/validators.py
libthirty.egg-info/PKG-INFO
libthirty.egg-info/SOURCES.txt
libthirty.egg-info/dependency_links.txt
libthirty.egg-info/requires.txt
libthirty.egg-info/top_level.txt
libthirty/ssl/StartSSL_CA.pem