Metadata-Version: 1.1
Name: libthirty
Version: 0.5.1
Summary: libthirty provides a python api to access the 30loopsplatform.
Home-page: https://github.com/30loops/libthirty
Author: Christo Buschek
Author-email: crito@30loops.net
License: UNKNOWN
Platform: UNKNOWN
Classifier: Development Status :: 4 - Beta
Classifier: Environment :: Console
Classifier: Intended Audience :: Developers
Classifier: License :: OSI Approved :: BSD License
Classifier: Operating System :: OS Independent
Classifier: Programming Language :: Python
Classifier: Programming Language :: Python :: 3
Classifier: Topic :: Internet :: WWW/HTTP
